ff3_cryptography/__init__.py
ff3_cryptography/algo.py
ff3_cryptography/fpe.py
ff3_cryptography-0.2.0.dist-info/LICENSE
ff3_cryptography-0.2.0.dist-info/METADATA
ff3_cryptography-0.2.0.dist-info/WHEEL
ff3_cryptography-0.2.0.dist-info/top_level.txt
ff3_cryptography-0.2.0.dist-info/RECORD
