Metadata-Version: 2.1
Name: ff3-cryptography
Version: 0.2.0
Summary: Implementation of ff3 based on python-fpe using cryptography instead of pycryptodome.
Home-page: https://github.com/stikkireddy/python-fpe-cryptography
Author: Sri Tikkireddy
Author-email: sri.tikkireddy@databricks.com
Classifier: Programming Language :: Python :: 3
Classifier: License :: OSI Approved :: Apache Software License
Classifier: Operating System :: OS Independent
Requires-Python: >=3.11
License-File: LICENSE
Requires-Dist: cryptography <44.0.0,>=43.0.1
